simpleciscooauth/__init__.py
simpleciscooauth-0.1.7.dist-info/METADATA
simpleciscooauth-0.1.7.dist-info/WHEEL
simpleciscooauth-0.1.7.dist-info/top_level.txt
simpleciscooauth-0.1.7.dist-info/RECORD
