Metadata-Version: 2.1
Name: simpleciscooauth
Version: 0.1.7
Summary: Simple Cisco OAuth Token Generation
Home-page: UNKNOWN
Author: Jason Smith
Author-email: UNKNOWN
License: MIT
Platform: UNKNOWN
